{
  "family": "cluttered",
  "workspace": [
    0,
    6,
    0,
    6
  ],
  "start": [
    1.9201568578687327,
    5.337965737747507,
    0.0
  ],
  "goal": [
    4.424845301154205,
    0.9971924248122452,
    0.0
  ],
  "obstacles": [
    {
      "id": 0,
      "shape_type": "trapezoid",
      "class_true": "safe",
      "radius": 0.2664,
      "center": [
        4.6677,
        2.3416
      ],
      "vertices": [
        [
          4.715549811480387,
          1.974121328473048
        ],
        [
          4.999775038630363,
          2.5059131938209385
        ],
        [
          4.515146496835806,
          2.611098480142744
        ],
        [
          4.358822621903319,
          2.318612954201404
        ]
      ]
    },
    {
      "id": 1,
      "shape_type": "rectangle",
      "class_true": "movable",
      "radius": 0.337,
      "center": [
        3.2883,
        5.198
      ],
      "vertices": [
        [
          3.3096623559822405,
          4.772100038897265
        ],
        [
          3.71023659997313,
          5.136085077720172
        ],
        [
          3.266889824287797,
          5.623998811950211
        ],
        [
          2.8663155802969076,
          5.260013773127304
        ]
      ]
    },
    {
      "id": 2,
      "shape_type": "triangle",
      "class_true": "movable",
      "radius": 0.2341,
      "center": [
        2.1582,
        1.3727
      ],
      "vertices": [
        [
          2.510506094984554,
          1.2862259868887749
        ],
        [
          2.061048518382926,
          1.7222800146736952
        ],
        [
          1.9029183657895052,
          1.1096256363036732
        ]
      ]
    },
    {
      "id": 3,
      "shape_type": "trapezoid",
      "class_true": "fragile",
      "radius": 0.3307,
      "center": [
        1.425,
        2.2256
      ],
      "vertices": [
        [
          1.4476007333113854,
          1.7645751047733484
        ],
        [
          1.8505015199641104,
          2.4042161450486184
        ],
        [
          1.2636303426516293,
          2.5728578811876557
        ],
        [
          1.0420349099926305,
          2.221055309036257
        ]
      ]
    },
    {
      "id": 4,
      "shape_type": "diamond",
      "class_true": "movable",
      "radius": 0.2236,
      "center": [
        2.7541,
        0.5453
      ],
      "vertices": [
        [
          2.5635958958644802,
          0.772344919121562
        ],
        [
          2.9571366116568787,
          0.7156261887850268
        ],
        [
          2.944543492303097,
          0.3182186867140123
        ],
        [
          2.5510027765106984,
          0.3749374170505475
        ]
      ]
    },
    {
      "id": 5,
      "shape_type": "trapezoid",
      "class_true": "movable",
      "radius": 0.2023,
      "center": [
        2.119,
        0.8081
      ],
      "vertices": [
        [
          2.070397969725647,
          0.5376557288606809
        ],
        [
          2.393367264879568,
          0.793007771979597
        ],
        [
          2.0707922239904866,
          1.0516359023351596
        ],
        [
          1.89315911165583,
          0.9111922786197557
        ]
      ]
    },
    {
      "id": 6,
      "shape_type": "diamond",
      "class_true": "safe",
      "radius": 0.22,
      "center": [
        2.5907,
        2.3965
      ],
      "vertices": [
        [
          2.4086217116628066,
          2.1732038623121235
        ],
        [
          2.3860854331793164,
          2.5632723120523946
        ],
        [
          2.7726885288522625,
          2.6198348946203676
        ],
        [
          2.7952248073357526,
          2.2297664448800965
        ]
      ]
    },
    {
      "id": 7,
      "shape_type": "diamond",
      "class_true": "movable",
      "radius": 0.1362,
      "center": [
        1.4538,
        4.3662
      ],
      "vertices": [
        [
          1.2839711939643104,
          4.450317234631555
        ],
        [
          1.522087541425401,
          4.504090769772946
        ],
        [
          1.6236516968901935,
          4.282109440975823
        ],
        [
          1.385535349429103,
          4.228335905834432
        ]
      ]
    },
    {
      "id": 8,
      "shape_type": "rectangle",
      "class_true": "movable",
      "radius": 0.424,
      "center": [
        4.0732,
        3.9538
      ],
      "vertices": [
        [
          4.603127226933088,
          3.827878274893879
        ],
        [
          4.03075654535192,
          4.496791988603086
        ],
        [
          3.543235699359428,
          4.0796340903766835
        ],
        [
          4.115606380940596,
          3.4107203766674763
        ]
      ]
    },
    {
      "id": 9,
      "shape_type": "diamond",
      "class_true": "movable",
      "radius": 0.2718,
      "center": [
        1.6162,
        3.2084
      ],
      "vertices": [
        [
          1.3271906725877793,
          3.1693184676372526
        ],
        [
          1.5628336939398686,
          3.6028394069042515
        ],
        [
          1.9051549482952523,
          3.247474528066403
        ],
        [
          1.669511926943163,
          2.813953588799404
        ]
      ]
    },
    {
      "id": 10,
      "shape_type": "circle",
      "class_true": "movable",
      "radius": 0.2816,
      "center": [
        3.4036,
        3.2743
      ],
      "vertices": [
        [
          3.68527889868956,
          3.2742949841280957
        ],
        [
          3.6849396380112447,
          3.260475036238145
        ],
        [
          3.683922673284988,
          3.2466883818131453
        ],
        [
          3.6822304544678914,
          3.2329682341111754
        ],
        [
          3.6798670582633064,
          3.219347646169792
        ],
        [
          3.676838178299698,
          3.2058594311783684
        ],
        [
          3.673151111414198,
          3.1925360834282475
        ],
        [
          3.6688147400738824,
          3.179409700031146
        ],
        [
          3.663839510977131,
          3.1665119035944036
        ],
        [
          3.6582374098866164,
          3.1538737660393497
        ],
        [
          3.652021932754552,
          3.1415257337463247
        ],
        [
          3.64520805320976,
          3.129497554206682
        ],
        [
          3.6378121864848896,
          3.1178182043584775
        ],
        [
          3.6298521498706826,
          3.1065158207784846
        ],
        [
          3.621347119792559,
          3.0956176318987203
        ],
        [
          3.6123175856129297,
          3.085149892410764
        ],
        [
          3.6027853002705275,
          3.0751378200159083
        ],
        [
          3.592773227875672,
          3.065605534673506
        ],
        [
          3.5823054883877155,
          3.0565760004938767
        ],
        [
          3.571407299507951,
          3.048070970415753
        ],
        [
          3.5601049159279587,
          3.040110933801546
        ],
        [
          3.5484255660797537,
          3.032715067076676
        ],
        [
          3.536397386540111,
          3.025901187531884
        ],
        [
          3.524049354247086,
          3.0196857103998194
        ],
        [
          3.511411216692032,
          3.0140836093093046
        ],
        [
          3.4985134202552897,
          3.0091083802125533
        ],
        [
          3.4853870368581883,
          3.0047720088722376
        ],
        [
          3.4720636891080674,
          3.0010849419867376
        ],
        [
          3.458575474116644,
          2.9980560620231294
        ],
        [
          3.4449548861752604,
          2.9956926658185443
        ],
        [
          3.4312347384732904,
          2.994000447001448
        ],
        [
          3.417448084048291,
          2.992983482275191
        ],
        [
          3.40362813615834,
          2.992644221596876
        ],
        [
          3.3898081882683893,
          2.992983482275191
        ],
        [
          3.3760215338433897,
          2.9940004470014476
        ],
        [
          3.3623013861414197,
          2.9956926658185443
        ],
        [
          3.348680798200036,
          2.9980560620231294
        ],
        [
          3.3351925832086127,
          3.0010849419867376
        ],
        [
          3.3218692354584918,
          3.0047720088722376
        ],
        [
          3.3087428520613904,
          3.0091083802125533
        ],
        [
          3.295845055624648,
          3.0140836093093046
        ],
        [
          3.283206918069594,
          3.0196857103998194
        ],
        [
          3.270858885776569,
          3.025901187531884
        ],
        [
          3.2588307062369264,
          3.032715067076676
        ],
        [
          3.2471513563887218,
          3.040110933801546
        ],
        [
          3.235848972808729,
          3.048070970415753
        ],
        [
          3.2249507839289646,
          3.0565760004938767
        ],
        [
          3.214483044441008,
          3.065605534673506
        ],
        [
          3.2044709720461526,
          3.0751378200159083
        ],
        [
          3.1949386867037504,
          3.085149892410764
        ],
        [
          3.185909152524121,
          3.0956176318987203
        ],
        [
          3.1774041224459975,
          3.1065158207784846
        ],
        [
          3.1694440858317905,
          3.1178182043584775
        ],
        [
          3.16204821910692,
          3.129497554206682
        ],
        [
          3.1552343395621283,
          3.1415257337463247
        ],
        [
          3.1490188624300637,
          3.1538737660393497
        ],
        [
          3.143416761339549,
          3.1665119035944036
        ],
        [
          3.1384415322427976,
          3.179409700031146
        ],
        [
          3.134105160902482,
          3.1925360834282475
        ],
        [
          3.130418094016982,
          3.2058594311783684
        ],
        [
          3.1273892140533737,
          3.219347646169792
        ],
        [
          3.1250258178487886,
          3.2329682341111754
        ],
        [
          3.1233335990316924,
          3.2466883818131453
        ],
        [
          3.1223166343054354,
          3.260475036238145
        ],
        [
          3.12197737362712,
          3.2742949841280957
        ],
        [
          3.1223166343054354,
          3.2881149320180465
        ],
        [
          3.123333599031692,
          3.301901586443046
        ],
        [
          3.1250258178487886,
          3.315621734145016
        ],
        [
          3.1273892140533737,
          3.3292423220863996
        ],
        [
          3.130418094016982,
          3.342730537077823
        ],
        [
          3.134105160902482,
          3.356053884827944
        ],
        [
          3.1384415322427976,
          3.3691802682250453
        ],
        [
          3.143416761339549,
          3.382078064661788
        ],
        [
          3.1490188624300637,
          3.3947162022168413
        ],
        [
          3.1552343395621283,
          3.4070642345098667
        ],
        [
          3.16204821910692,
          3.4190924140495094
        ],
        [
          3.1694440858317905,
          3.430771763897714
        ],
        [
          3.1774041224459975,
          3.442074147477707
        ],
        [
          3.185909152524121,
          3.452972336357471
        ],
        [
          3.1949386867037504,
          3.4634400758454276
        ],
        [
          3.2044709720461526,
          3.473452148240283
        ],
        [
          3.214483044441008,
          3.4829844335826854
        ],
        [
          3.224950783928964,
          3.4920139677623143
        ],
        [
          3.235848972808729,
          3.5005189978404383
        ],
        [
          3.2471513563887218,
          3.5084790344546453
        ],
        [
          3.2588307062369264,
          3.5158749011795156
        ],
        [
          3.270858885776569,
          3.5226887807243075
        ],
        [
          3.283206918069594,
          3.528904257856372
        ],
        [
          3.295845055624648,
          3.5345063589468864
        ],
        [
          3.3087428520613904,
          3.539481588043638
        ],
        [
          3.3218692354584918,
          3.543817959383954
        ],
        [
          3.3351925832086127,
          3.547505026269454
        ],
        [
          3.348680798200036,
          3.5505339062330616
        ],
        [
          3.3623013861414197,
          3.552897302437647
        ],
        [
          3.3760215338433897,
          3.554589521254744
        ],
        [
          3.3898081882683893,
          3.5556064859810004
        ],
        [
          3.40362813615834,
          3.5559457466593156
        ],
        [
          3.417448084048291,
          3.5556064859810004
        ],
        [
          3.4312347384732904,
          3.554589521254744
        ],
        [
          3.4449548861752604,
          3.552897302437647
        ],
        [
          3.458575474116644,
          3.550533906233062
        ],
        [
          3.4720636891080674,
          3.547505026269454
        ],
        [
          3.4853870368581883,
          3.543817959383954
        ],
        [
          3.4985134202552897,
          3.539481588043638
        ],
        [
          3.511411216692032,
          3.534506358946887
        ],
        [
          3.524049354247086,
          3.528904257856372
        ],
        [
          3.536397386540111,
          3.5226887807243075
        ],
        [
          3.5484255660797537,
          3.5158749011795156
        ],
        [
          3.5601049159279583,
          3.5084790344546453
        ],
        [
          3.571407299507951,
          3.5005189978404383
        ],
        [
          3.582305488387716,
          3.4920139677623148
        ],
        [
          3.592773227875672,
          3.4829844335826854
        ],
        [
          3.6027853002705275,
          3.473452148240283
        ],
        [
          3.6123175856129297,
          3.4634400758454276
        ],
        [
          3.6213471197925586,
          3.4529723363574716
        ],
        [
          3.6298521498706826,
          3.442074147477707
        ],
        [
          3.6378121864848896,
          3.430771763897714
        ],
        [
          3.64520805320976,
          3.4190924140495094
        ],
        [
          3.652021932754552,
          3.4070642345098667
        ],
        [
          3.6582374098866164,
          3.394716202216842
        ],
        [
          3.6638395109771307,
          3.382078064661788
        ],
        [
          3.6688147400738824,
          3.3691802682250453
        ],
        [
          3.673151111414198,
          3.356053884827944
        ],
        [
          3.676838178299698,
          3.342730537077823
        ],
        [
          3.679867058263306,
          3.3292423220863996
        ],
        [
          3.6822304544678914,
          3.315621734145016
        ],
        [
          3.683922673284988,
          3.301901586443046
        ],
        [
          3.6849396380112447,
          3.2881149320180465
        ]
      ]
    },
    {
      "id": 11,
      "shape_type": "rectangle",
      "class_true": "movable",
      "radius": 0.4132,
      "center": [
        2.2247,
        4.4069
      ],
      "vertices": [
        [
          2.6345734369650793,
          4.085898209481387
        ],
        [
          2.48275734394536,
          4.8589731938530685
        ],
        [
          1.8148088900411843,
          4.727801798244256
        ],
        [
          1.966624983060904,
          3.9547268138725746
        ]
      ]
    },
    {
      "id": 12,
      "shape_type": "trapezoid",
      "class_true": "fragile",
      "radius": 0.4015,
      "center": [
        3.2193,
        1.2863
      ],
      "vertices": [
        [
          3.2341084856369187,
          0.7431744294023623
        ],
        [
          3.7618359147796,
          1.316783811139382
        ],
        [
          3.0260955721048237,
          1.75537054987101
        ],
        [
          2.735845486076349,
          1.4398853899156492
        ]
      ]
    },
    {
      "id": 13,
      "shape_type": "circle",
      "class_true": "safe",
      "radius": 0.2582,
      "center": [
        5.4099,
        2.6971
      ],
      "vertices": [
        [
          5.6681446861665865,
          2.6970669576707307
        ],
        [
          5.667833570728251,
          2.684393519750049
        ],
        [
          5.666900973917586,
          2.6717506132513797
        ],
        [
          5.665349142441992,
          2.659168696043867
        ],
        [
          5.663181814799421,
          2.646678079068109
        ],
        [
          5.660404212271998,
          2.634308853314449
        ],
        [
          5.657023026347501,
          2.6220908173311446
        ],
        [
          5.653046402598979,
          2.610053405437052
        ],
        [
          5.648483921061353,
          2.5982256168117774
        ],
        [
          5.643346573152273,
          2.5866359456341113
        ],
        [
          5.637646735192833,
          2.5753123124370556
        ],
        [
          5.631398138591921,
          2.564281996844815
        ],
        [
          5.624615836766063,
          2.553571571853793
        ],
        [
          5.6173161688744155,
          2.5432068398159156
        ],
        [
          5.609516720456306,
          2.5332127702785048
        ],
        [
          5.601236281066125,
          2.523613439830454
        ],
        [
          5.592494799007643,
          2.514431974099614
        ],
        [
          5.583313333276803,
          2.5056904920411323
        ],
        [
          5.573714002828752,
          2.4974100526509506
        ],
        [
          5.563719933291342,
          2.4896106042328414
        ],
        [
          5.5533552012534635,
          2.482310936341194
        ],
        [
          5.542644776262442,
          2.4755286345153356
        ],
        [
          5.531614460670202,
          2.469280037914424
        ],
        [
          5.520290827473146,
          2.463580199954983
        ],
        [
          5.508701156295479,
          2.4584428520459043
        ],
        [
          5.496873367670205,
          2.453880370508278
        ],
        [
          5.484835955776113,
          2.449903746759756
        ],
        [
          5.472617919792808,
          2.446522560835259
        ],
        [
          5.460248694039148,
          2.443744958307836
        ],
        [
          5.44775807706339,
          2.4415776306652646
        ],
        [
          5.435176159855877,
          2.4400257991896717
        ],
        [
          5.422533253357209,
          2.4390932023790057
        ],
        [
          5.409859815436526,
          2.43878208694067
        ],
        [
          5.397186377515844,
          2.4390932023790057
        ],
        [
          5.384543471017175,
          2.4400257991896717
        ],
        [
          5.371961553809663,
          2.4415776306652646
        ],
        [
          5.359470936833905,
          2.443744958307836
        ],
        [
          5.347101711080245,
          2.446522560835259
        ],
        [
          5.33488367509694,
          2.449903746759756
        ],
        [
          5.322846263202847,
          2.453880370508278
        ],
        [
          5.3110184745775735,
          2.4584428520459043
        ],
        [
          5.299428803399907,
          2.463580199954983
        ],
        [
          5.288105170202851,
          2.469280037914424
        ],
        [
          5.2770748546106105,
          2.4755286345153356
        ],
        [
          5.266364429619589,
          2.482310936341194
        ],
        [
          5.255999697581711,
          2.489610604232841
        ],
        [
          5.2460056280443,
          2.4974100526509506
        ],
        [
          5.2364062975962495,
          2.5056904920411323
        ],
        [
          5.22722483186541,
          2.514431974099614
        ],
        [
          5.218483349806927,
          2.523613439830454
        ],
        [
          5.210202910416746,
          2.5332127702785048
        ],
        [
          5.202403461998637,
          2.5432068398159156
        ],
        [
          5.1951037941069895,
          2.553571571853793
        ],
        [
          5.188321492281132,
          2.564281996844815
        ],
        [
          5.18207289568022,
          2.575312312437055
        ],
        [
          5.176373057720779,
          2.5866359456341113
        ],
        [
          5.171235709811699,
          2.5982256168117774
        ],
        [
          5.166673228274074,
          2.610053405437052
        ],
        [
          5.162696604525552,
          2.6220908173311446
        ],
        [
          5.159315418601055,
          2.634308853314449
        ],
        [
          5.156537816073632,
          2.646678079068109
        ],
        [
          5.15437048843106,
          2.659168696043867
        ],
        [
          5.152818656955467,
          2.6717506132513797
        ],
        [
          5.151886060144801,
          2.684393519750049
        ],
        [
          5.151574944706466,
          2.6970669576707307
        ],
        [
          5.151886060144801,
          2.7097403955914126
        ],
        [
          5.152818656955467,
          2.7223833020900816
        ],
        [
          5.15437048843106,
          2.734965219297594
        ],
        [
          5.156537816073632,
          2.7474558362733523
        ],
        [
          5.159315418601055,
          2.759825062027012
        ],
        [
          5.162696604525552,
          2.772043098010317
        ],
        [
          5.166673228274074,
          2.7840805099044093
        ],
        [
          5.171235709811699,
          2.795908298529684
        ],
        [
          5.176373057720779,
          2.80749796970735
        ],
        [
          5.18207289568022,
          2.8188216029044058
        ],
        [
          5.188321492281132,
          2.8298519184966464
        ],
        [
          5.1951037941069895,
          2.8405623434876683
        ],
        [
          5.202403461998637,
          2.850927075525546
        ],
        [
          5.210202910416746,
          2.8609211450629566
        ],
        [
          5.218483349806927,
          2.8705204755110074
        ],
        [
          5.227224831865409,
          2.8797019412418474
        ],
        [
          5.2364062975962495,
          2.888443423300329
        ],
        [
          5.2460056280443,
          2.8967238626905107
        ],
        [
          5.255999697581711,
          2.9045233111086204
        ],
        [
          5.266364429619589,
          2.9118229790002674
        ],
        [
          5.2770748546106105,
          2.9186052808261254
        ],
        [
          5.288105170202851,
          2.9248538774270374
        ],
        [
          5.299428803399906,
          2.9305537153864782
        ],
        [
          5.311018474577573,
          2.935691063295557
        ],
        [
          5.322846263202847,
          2.9402535448331832
        ],
        [
          5.33488367509694,
          2.944230168581705
        ],
        [
          5.347101711080245,
          2.9476113545062024
        ],
        [
          5.359470936833905,
          2.9503889570336255
        ],
        [
          5.371961553809663,
          2.952556284676197
        ],
        [
          5.384543471017175,
          2.9541081161517897
        ],
        [
          5.397186377515844,
          2.9550407129624556
        ],
        [
          5.409859815436526,
          2.9553518284007914
        ],
        [
          5.422533253357208,
          2.9550407129624556
        ],
        [
          5.435176159855877,
          2.9541081161517897
        ],
        [
          5.44775807706339,
          2.952556284676197
        ],
        [
          5.460248694039148,
          2.9503889570336255
        ],
        [
          5.472617919792808,
          2.9476113545062024
        ],
        [
          5.484835955776113,
          2.944230168581705
        ],
        [
          5.496873367670204,
          2.9402535448331832
        ],
        [
          5.508701156295479,
          2.935691063295557
        ],
        [
          5.520290827473146,
          2.9305537153864782
        ],
        [
          5.531614460670202,
          2.9248538774270374
        ],
        [
          5.542644776262442,
          2.918605280826126
        ],
        [
          5.5533552012534635,
          2.9118229790002674
        ],
        [
          5.563719933291341,
          2.9045233111086204
        ],
        [
          5.573714002828752,
          2.8967238626905107
        ],
        [
          5.583313333276803,
          2.888443423300329
        ],
        [
          5.592494799007643,
          2.8797019412418474
        ],
        [
          5.601236281066125,
          2.8705204755110074
        ],
        [
          5.609516720456306,
          2.8609211450629566
        ],
        [
          5.6173161688744155,
          2.850927075525546
        ],
        [
          5.624615836766063,
          2.8405623434876683
        ],
        [
          5.631398138591921,
          2.8298519184966464
        ],
        [
          5.637646735192833,
          2.818821602904406
        ],
        [
          5.643346573152273,
          2.80749796970735
        ],
        [
          5.648483921061353,
          2.795908298529684
        ],
        [
          5.653046402598979,
          2.7840805099044093
        ],
        [
          5.657023026347501,
          2.772043098010317
        ],
        [
          5.660404212271998,
          2.759825062027012
        ],
        [
          5.663181814799421,
          2.7474558362733523
        ],
        [
          5.665349142441992,
          2.7349652192975946
        ],
        [
          5.666900973917586,
          2.7223833020900816
        ],
        [
          5.667833570728251,
          2.7097403955914126
        ]
      ]
    },
    {
      "id": 14,
      "shape_type": "trapezoid",
      "class_true": "movable",
      "radius": 0.3343,
      "center": [
        3.9849,
        2.8051
      ],
      "vertices": [
        [
          3.787688633004119,
          2.378275380570887
        ],
        [
          4.305058163532421,
          2.460758866951029
        ],
        [
          4.0525189380359885,
          3.296068858244582
        ],
        [
          3.7679656962454224,
          3.250702940735504
        ]
      ]
    },
    {
      "id": 15,
      "shape_type": "rectangle",
      "class_true": "movable",
      "radius": 0.1899,
      "center": [
        2.8548,
        4.7929
      ],
      "vertices": [
        [
          2.709619922291904,
          4.600565368412198
        ],
        [
          3.074132394807303,
          4.693099954247821
        ],
        [
          2.999993762474375,
          4.985147040605256
        ],
        [
          2.6354812899589763,
          4.892612454769632
        ]
      ]
    },
    {
      "id": 16,
      "shape_type": "trapezoid",
      "class_true": "fragile",
      "radius": 0.2257,
      "center": [
        1.2301,
        4.9643
      ],
      "vertices": [
        [
          0.9822923863906611,
          4.759344900416726
        ],
        [
          1.522178710682056,
          4.829665359045252
        ],
        [
          1.351738704687754,
          5.189777218085512
        ],
        [
          1.0548012263274869,
          5.151100965839823
        ]
      ]
    },
    {
      "id": 17,
      "shape_type": "circle",
      "class_true": "movable",
      "radius": 0.2918,
      "center": [
        5.2863,
        2.0547
      ],
      "vertices": [
        [
          5.578177895292187,
          2.054741157411364
        ],
        [
          5.577826367620194,
          2.0404215075983023
        ],
        [
          5.576772631465167,
          2.026136355075894
        ],
        [
          5.5750192253698,
          2.0119201140277965
        ],
        [
          5.572570373442957,
          1.9978070326238904
        ],
        [
          5.569431975183424,
          1.9838311105134376
        ],
        [
          5.565611591267499,
          1.9700260169169486
        ],
        [
          5.56111842533466,
          1.9564250095140803
        ],
        [
          5.555963301815198,
          1.9430608543229744
        ],
        [
          5.550158639853204,
          1.9299657467640474
        ],
        [
          5.543718423387773,
          1.917171234098405
        ],
        [
          5.536658167464467,
          1.9047081394277259
        ],
        [
          5.528994880858211,
          1.8926064874387096
        ],
        [
          5.5207470250976645,
          1.8808954320709772
        ],
        [
          5.51193446998978,
          1.869603186282677
        ],
        [
          5.502578445751702,
          1.858756954082997
        ],
        [
          5.4927014918653105,
          1.8483828649953236
        ],
        [
          5.482327402777637,
          1.8385059111089321
        ],
        [
          5.471481170577957,
          1.829149886870854
        ],
        [
          5.460188924789657,
          1.8203373317629694
        ],
        [
          5.448477869421924,
          1.8120894760024222
        ],
        [
          5.436376217432908,
          1.8044261893961662
        ],
        [
          5.423913122762229,
          1.7973659334728607
        ],
        [
          5.411118610096587,
          1.79092571700743
        ],
        [
          5.39802350253766,
          1.785121055045436
        ],
        [
          5.384659347346553,
          1.779965931525973
        ],
        [
          5.371058339943685,
          1.7754727655931357
        ],
        [
          5.357253246347196,
          1.7716523816772103
        ],
        [
          5.343277324236744,
          1.7685139834176768
        ],
        [
          5.329164242832838,
          1.7660651314908336
        ],
        [
          5.31494800178474,
          1.7643117253954665
        ],
        [
          5.3006628492623316,
          1.7632579892404396
        ],
        [
          5.28634319944927,
          1.7629064615684467
        ],
        [
          5.2720235496362085,
          1.7632579892404396
        ],
        [
          5.2577383971138,
          1.7643117253954665
        ],
        [
          5.243522156065703,
          1.7660651314908336
        ],
        [
          5.229409074661796,
          1.7685139834176768
        ],
        [
          5.215433152551344,
          1.7716523816772103
        ],
        [
          5.201628058954855,
          1.7754727655931357
        ],
        [
          5.188027051551987,
          1.779965931525973
        ],
        [
          5.17466289636088,
          1.785121055045436
        ],
        [
          5.161567788801953,
          1.79092571700743
        ],
        [
          5.148773276136311,
          1.7973659334728607
        ],
        [
          5.136310181465632,
          1.8044261893961662
        ],
        [
          5.124208529476616,
          1.8120894760024222
        ],
        [
          5.112497474108883,
          1.8203373317629694
        ],
        [
          5.101205228320583,
          1.829149886870854
        ],
        [
          5.090358996120903,
          1.8385059111089321
        ],
        [
          5.0799849070332295,
          1.8483828649953236
        ],
        [
          5.070107953146838,
          1.858756954082997
        ],
        [
          5.06075192890876,
          1.869603186282677
        ],
        [
          5.0519393738008755,
          1.8808954320709772
        ],
        [
          5.043691518040329,
          1.8926064874387096
        ],
        [
          5.036028231434073,
          1.9047081394277259
        ],
        [
          5.028967975510767,
          1.917171234098405
        ],
        [
          5.022527759045336,
          1.9299657467640474
        ],
        [
          5.016723097083342,
          1.9430608543229744
        ],
        [
          5.01156797356388,
          1.9564250095140803
        ],
        [
          5.007074807631041,
          1.9700260169169486
        ],
        [
          5.003254423715116,
          1.9838311105134374
        ],
        [
          5.000116025455583,
          1.9978070326238901
        ],
        [
          4.99766717352874,
          2.0119201140277965
        ],
        [
          4.995913767433373,
          2.0261363550758937
        ],
        [
          4.994860031278346,
          2.0404215075983023
        ],
        [
          4.994508503606353,
          2.054741157411364
        ],
        [
          4.994860031278346,
          2.069060807224425
        ],
        [
          4.995913767433373,
          2.0833459597468336
        ],
        [
          4.99766717352874,
          2.0975622007949313
        ],
        [
          5.000116025455583,
          2.1116752821988376
        ],
        [
          5.003254423715116,
          2.1256512043092903
        ],
        [
          5.007074807631041,
          2.139456297905779
        ],
        [
          5.01156797356388,
          2.1530573053086473
        ],
        [
          5.016723097083342,
          2.1664214604997536
        ],
        [
          5.022527759045336,
          2.17951656805868
        ],
        [
          5.028967975510767,
          2.1923110807243225
        ],
        [
          5.036028231434073,
          2.2047741753950016
        ],
        [
          5.043691518040329,
          2.216875827384018
        ],
        [
          5.0519393738008755,
          2.2285868827517503
        ],
        [
          5.06075192890876,
          2.239879128540051
        ],
        [
          5.070107953146838,
          2.250725360739731
        ],
        [
          5.0799849070332295,
          2.261099449827404
        ],
        [
          5.090358996120903,
          2.2709764037137954
        ],
        [
          5.101205228320583,
          2.2803324279518735
        ],
        [
          5.112497474108883,
          2.2891449830597583
        ],
        [
          5.124208529476616,
          2.2973928388203055
        ],
        [
          5.136310181465632,
          2.3050561254265616
        ],
        [
          5.148773276136311,
          2.312116381349867
        ],
        [
          5.161567788801953,
          2.3185565978152978
        ],
        [
          5.17466289636088,
          2.324361259777292
        ],
        [
          5.188027051551987,
          2.3295163832967547
        ],
        [
          5.201628058954855,
          2.334009549229592
        ],
        [
          5.215433152551344,
          2.3378299331455175
        ],
        [
          5.229409074661796,
          2.3409683314050507
        ],
        [
          5.243522156065702,
          2.343417183331894
        ],
        [
          5.2577383971138,
          2.345170589427261
        ],
        [
          5.2720235496362085,
          2.346224325582288
        ],
        [
          5.28634319944927,
          2.346575853254281
        ],
        [
          5.3006628492623316,
          2.346224325582288
        ],
        [
          5.31494800178474,
          2.345170589427261
        ],
        [
          5.329164242832838,
          2.343417183331894
        ],
        [
          5.343277324236744,
          2.340968331405051
        ],
        [
          5.357253246347196,
          2.3378299331455175
        ],
        [
          5.371058339943685,
          2.334009549229592
        ],
        [
          5.384659347346553,
          2.3295163832967547
        ],
        [
          5.39802350253766,
          2.324361259777292
        ],
        [
          5.411118610096587,
          2.3185565978152978
        ],
        [
          5.423913122762229,
          2.312116381349867
        ],
        [
          5.436376217432908,
          2.3050561254265616
        ],
        [
          5.448477869421924,
          2.2973928388203055
        ],
        [
          5.460188924789657,
          2.2891449830597583
        ],
        [
          5.471481170577957,
          2.2803324279518735
        ],
        [
          5.482327402777637,
          2.2709764037137954
        ],
        [
          5.4927014918653105,
          2.2610994498274044
        ],
        [
          5.502578445751702,
          2.250725360739731
        ],
        [
          5.51193446998978,
          2.239879128540051
        ],
        [
          5.5207470250976645,
          2.2285868827517503
        ],
        [
          5.528994880858211,
          2.216875827384018
        ],
        [
          5.536658167464467,
          2.204774175395002
        ],
        [
          5.543718423387773,
          2.1923110807243225
        ],
        [
          5.550158639853204,
          2.1795165680586805
        ],
        [
          5.555963301815198,
          2.1664214604997536
        ],
        [
          5.56111842533466,
          2.1530573053086473
        ],
        [
          5.565611591267499,
          2.139456297905779
        ],
        [
          5.569431975183424,
          2.1256512043092903
        ],
        [
          5.572570373442957,
          2.1116752821988376
        ],
        [
          5.5750192253698,
          2.0975622007949313
        ],
        [
          5.576772631465167,
          2.0833459597468336
        ],
        [
          5.577826367620194,
          2.0690608072244254
        ]
      ]
    },
    {
      "id": 18,
      "shape_type": "diamond",
      "class_true": "fragile",
      "radius": 0.3107,
      "center": [
        5.3971,
        5.3236
      ],
      "vertices": [
        [
          5.189970706905676,
          5.598694965510945
        ],
        [
          5.748799865568341,
          5.588503324703451
        ],
        [
          5.6042416942888025,
          5.048598857940777
        ],
        [
          5.045412535626137,
          5.058790498748271
        ]
      ]
    },
    {
      "id": 19,
      "shape_type": "triangle",
      "class_true": "safe",
      "radius": 0.2811,
      "center": [
        3.1647,
        3.9029
      ],
      "vertices": [
        [
          3.455876441376959,
          3.616141412071662
        ],
        [
          3.4090578633728743,
          4.230446921039876
        ],
        [
          2.629122085131342,
          3.8620681590629955
        ]
      ]
    },
    {
      "id": 20,
      "shape_type": "diamond",
      "class_true": "safe",
      "radius": 0.1362,
      "center": [
        2.2944,
        1.7783
      ],
      "vertices": [
        [
          2.248268392774517,
          1.6332199016232307
        ],
        [
          2.1120138431500224,
          1.8362131256904382
        ],
        [
          2.340452654647047,
          1.923318009092002
        ],
        [
          2.4767072042715417,
          1.7203247850247945
        ]
      ]
    },
    {
      "id": 21,
      "shape_type": "rectangle",
      "class_true": "movable",
      "radius": 0.1899,
      "center": [
        5.3457,
        3.8581
      ],
      "vertices": [
        [
          5.580889542253603,
          3.8192380302899536
        ],
        [
          5.402715314403387,
          4.0895622950987915
        ],
        [
          5.11060950035256,
          3.8970315657324517
        ],
        [
          5.288783728202776,
          3.626707300923614
        ]
      ]
    },
    {
      "id": 22,
      "shape_type": "diamond",
      "class_true": "fragile",
      "radius": 0.1731,
      "center": [
        0.8178,
        0.95
      ],
      "vertices": [
        [
          0.6463993989775393,
          1.0083487661703898
        ],
        [
          0.9014864044493534,
          1.1960583523161814
        ],
        [
          0.9891305260382856,
          0.8917184485202675
        ],
        [
          0.7340435205664715,
          0.704008862374476
        ]
      ]
    },
    {
      "id": 23,
      "shape_type": "circle",
      "class_true": "fragile",
      "radius": 0.1722,
      "center": [
        2.3879,
        3.4849
      ],
      "vertices": [
        [
          2.560107620246492,
          3.4848838338236074
        ],
        [
          2.5599001910776717,
          3.476434106262528
        ],
        [
          2.559278403286247,
          3.4680047348352514
        ],
        [
          2.55824375481347,
          3.4596160266358726
        ],
        [
          2.5567987382181356,
          3.4512881907972073
        ],
        [
          2.5549468346717905,
          3.4430412898052234
        ],
        [
          2.552692505572286,
          3.434895191166754
        ],
        [
          2.5500411817958786,
          3.426869519546933
        ],
        [
          2.5469992506137733,
          3.418983609491658
        ],
        [
          2.5435740403046307,
          3.411256458848977
        ],
        [
          2.5397738025000978,
          3.4037066830016056
        ],
        [
          2.5356076923059074,
          3.3963524700208434
        ],
        [
          2.531085746246425,
          3.389211536849914
        ],
        [
          2.5262188580857847,
          3.3823010866222973
        ],
        [
          2.5210187525838537,
          3.375637767217876
        ],
        [
          2.515497957250262,
          3.3692376311567336
        ],
        [
          2.5096697721645325,
          3.3631160969272265
        ],
        [
          2.5035482379350253,
          3.357287911841497
        ],
        [
          2.497148101873883,
          3.3517671165079053
        ],
        [
          2.4904847824694616,
          3.346567011005974
        ],
        [
          2.483574332241845,
          3.341700122845334
        ],
        [
          2.4764333990709155,
          3.3371781767858515
        ],
        [
          2.4690791860901533,
          3.333012066591661
        ],
        [
          2.4615294102427825,
          3.329211828787128
        ],
        [
          2.453802259600101,
          3.3257866184779856
        ],
        [
          2.445916349544826,
          3.3227446872958804
        ],
        [
          2.437890677925005,
          3.3200933635194727
        ],
        [
          2.4297445792865355,
          3.3178390344199684
        ],
        [
          2.4214976782945516,
          3.3159871308736233
        ],
        [
          2.4131698424558863,
          3.314542114278289
        ],
        [
          2.4047811342565075,
          3.313507465805512
        ],
        [
          2.396351762829231,
          3.312885678014087
        ],
        [
          2.3879020352681515,
          3.312678248845267
        ],
        [
          2.379452307707072,
          3.312885678014087
        ],
        [
          2.3710229362797954,
          3.313507465805512
        ],
        [
          2.3626342280804167,
          3.314542114278289
        ],
        [
          2.3543063922417513,
          3.3159871308736233
        ],
        [
          2.3460594912497674,
          3.3178390344199684
        ],
        [
          2.337913392611298,
          3.3200933635194727
        ],
        [
          2.329887720991477,
          3.3227446872958804
        ],
        [
          2.322001810936202,
          3.3257866184779856
        ],
        [
          2.314274660293521,
          3.329211828787128
        ],
        [
          2.3067248844461496,
          3.333012066591661
        ],
        [
          2.2993706714653874,
          3.3371781767858515
        ],
        [
          2.292229738294458,
          3.341700122845334
        ],
        [
          2.2853192880668414,
          3.346567011005974
        ],
        [
          2.27865596866242,
          3.3517671165079053
        ],
        [
          2.2722558326012776,
          3.357287911841497
        ],
        [
          2.2661342983717705,
          3.3631160969272265
        ],
        [
          2.260306113286041,
          3.3692376311567336
        ],
        [
          2.2547853179524493,
          3.375637767217876
        ],
        [
          2.2495852124505182,
          3.3823010866222973
        ],
        [
          2.244718324289878,
          3.389211536849914
        ],
        [
          2.2401963782303955,
          3.3963524700208434
        ],
        [
          2.236030268036205,
          3.4037066830016056
        ],
        [
          2.232230030231672,
          3.411256458848977
        ],
        [
          2.2288048199225297,
          3.418983609491658
        ],
        [
          2.225762888740425,
          3.426869519546933
        ],
        [
          2.2231115649640167,
          3.434895191166754
        ],
        [
          2.2208572358645124,
          3.4430412898052234
        ],
        [
          2.2190053323181673,
          3.4512881907972073
        ],
        [
          2.217560315722833,
          3.459616026635872
        ],
        [
          2.216525667250056,
          3.4680047348352514
        ],
        [
          2.215903879458631,
          3.476434106262528
        ],
        [
          2.215696450289811,
          3.4848838338236074
        ],
        [
          2.215903879458631,
          3.493333561384687
        ],
        [
          2.216525667250056,
          3.5017629328119635
        ],
        [
          2.217560315722833,
          3.5101516410113422
        ],
        [
          2.2190053323181673,
          3.5184794768500076
        ],
        [
          2.2208572358645124,
          3.5267263778419915
        ],
        [
          2.2231115649640167,
          3.534872476480461
        ],
        [
          2.2257628887404244,
          3.542898148100282
        ],
        [
          2.2288048199225297,
          3.550784058155557
        ],
        [
          2.232230030231672,
          3.558511208798238
        ],
        [
          2.236030268036205,
          3.5660609846456093
        ],
        [
          2.2401963782303955,
          3.5734151976263715
        ],
        [
          2.2447183242898774,
          3.580556130797301
        ],
        [
          2.2495852124505182,
          3.5874665810249176
        ],
        [
          2.2547853179524493,
          3.5941299004293388
        ],
        [
          2.260306113286041,
          3.6005300364904813
        ],
        [
          2.2661342983717705,
          3.6066515707199884
        ],
        [
          2.2722558326012776,
          3.612479755805718
        ],
        [
          2.27865596866242,
          3.6180005511393096
        ],
        [
          2.2853192880668414,
          3.6232006566412407
        ],
        [
          2.292229738294458,
          3.628067544801881
        ],
        [
          2.2993706714653874,
          3.6325894908613634
        ],
        [
          2.3067248844461496,
          3.6367556010555537
        ],
        [
          2.3142746602935205,
          3.6405558388600867
        ],
        [
          2.322001810936202,
          3.6439810491692293
        ],
        [
          2.329887720991477,
          3.6470229803513345
        ],
        [
          2.337913392611298,
          3.649674304127742
        ],
        [
          2.3460594912497674,
          3.6519286332272465
        ],
        [
          2.3543063922417513,
          3.6537805367735916
        ],
        [
          2.3626342280804162,
          3.655225553368926
        ],
        [
          2.3710229362797954,
          3.656260201841703
        ],
        [
          2.379452307707072,
          3.6568819896331277
        ],
        [
          2.3879020352681515,
          3.657089418801948
        ],
        [
          2.396351762829231,
          3.6568819896331277
        ],
        [
          2.4047811342565075,
          3.656260201841703
        ],
        [
          2.4131698424558867,
          3.655225553368926
        ],
        [
          2.4214976782945516,
          3.6537805367735916
        ],
        [
          2.4297445792865355,
          3.6519286332272465
        ],
        [
          2.437890677925005,
          3.649674304127742
        ],
        [
          2.445916349544826,
          3.6470229803513345
        ],
        [
          2.453802259600101,
          3.6439810491692293
        ],
        [
          2.4615294102427825,
          3.6405558388600867
        ],
        [
          2.4690791860901533,
          3.6367556010555537
        ],
        [
          2.4764333990709155,
          3.6325894908613634
        ],
        [
          2.483574332241845,
          3.6280675448018815
        ],
        [
          2.4904847824694616,
          3.6232006566412407
        ],
        [
          2.497148101873883,
          3.6180005511393096
        ],
        [
          2.5035482379350253,
          3.612479755805718
        ],
        [
          2.5096697721645325,
          3.6066515707199884
        ],
        [
          2.515497957250262,
          3.6005300364904813
        ],
        [
          2.5210187525838537,
          3.5941299004293388
        ],
        [
          2.5262188580857847,
          3.5874665810249176
        ],
        [
          2.531085746246425,
          3.580556130797301
        ],
        [
          2.5356076923059074,
          3.5734151976263715
        ],
        [
          2.5397738025000978,
          3.5660609846456093
        ],
        [
          2.5435740403046307,
          3.5585112087982385
        ],
        [
          2.5469992506137733,
          3.550784058155557
        ],
        [
          2.5500411817958786,
          3.542898148100282
        ],
        [
          2.552692505572286,
          3.534872476480461
        ],
        [
          2.5549468346717905,
          3.5267263778419915
        ],
        [
          2.5567987382181356,
          3.5184794768500076
        ],
        [
          2.55824375481347,
          3.5101516410113427
        ],
        [
          2.559278403286247,
          3.5017629328119635
        ],
        [
          2.5599001910776717,
          3.493333561384687
        ]
      ]
    },
    {
      "id": 24,
      "shape_type": "rectangle",
      "class_true": "movable",
      "radius": 0.28,
      "center": [
        0.7733,
        4.4522
      ],
      "vertices": [
        [
          0.7889239769215365,
          4.093222382819995
        ],
        [
          1.1204227194759766,
          4.35946177889191
        ],
        [
          0.7575862580464473,
          4.811235004385189
        ],
        [
          0.4260875154920071,
          4.5449956083132745
        ]
      ]
    },
    {
      "id": 25,
      "shape_type": "rectangle",
      "class_true": "safe",
      "radius": 0.3343,
      "center": [
        0.8641,
        3.6588
      ],
      "vertices": [
        [
          1.2969652692303433,
          3.764558529959464
        ],
        [
          0.56798836676378,
          3.9918630156998476
        ],
        [
          0.43114898983008904,
          3.5530122609175185
        ],
        [
          1.1601258922966524,
          3.325707775177135
        ]
      ]
    },
    {
      "id": 26,
      "shape_type": "diamond",
      "class_true": "movable",
      "radius": 0.1634,
      "center": [
        0.7256,
        1.9281
      ],
      "vertices": [
        [
          0.6630907110137226,
          1.6870974718595348
        ],
        [
          0.5625493826268488,
          1.9703714432830406
        ],
        [
          0.7880992665604002,
          2.169067068442237
        ],
        [
          0.888640594947274,
          1.8857930970187313
        ]
      ]
    },
    {
      "id": 27,
      "shape_type": "trapezoid",
      "class_true": "fragile",
      "radius": 0.2352,
      "center": [
        4.2472,
        4.7994
      ],
      "vertices": [
        [
          4.567897024212671,
          4.843569834271441
        ],
        [
          4.287176574624792,
          5.1206334940205585
        ],
        [
          3.951082383062337,
          4.653768343932832
        ],
        [
          4.1054786303356705,
          4.501383331070818
        ]
      ]
    },
    {
      "id": 28,
      "shape_type": "diamond",
      "class_true": "movable",
      "radius": 0.2422,
      "center": [
        0.7468,
        5.3502
      ],
      "vertices": [
        [
          0.6346556953192473,
          5.524845776556368
        ],
        [
          1.1204753823793303,
          5.590252516158339
        ],
        [
          0.8590283907706271,
          5.175590870356275
        ],
        [
          0.37320870371054415,
          5.110184130754304
        ]
      ]
    },
    {
      "id": 29,
      "shape_type": "trapezoid",
      "class_true": "safe",
      "radius": 0.2941,
      "center": [
        5.2793,
        1.1403
      ],
      "vertices": [
        [
          5.013548178093778,
          0.8439380089324631
        ],
        [
          5.587215651311398,
          0.8879356702972709
        ],
        [
          5.411542979300928,
          1.4856017766857992
        ],
        [
          5.096025869031236,
          1.4614030629351547
        ]
      ]
    },
    {
      "id": 30,
      "shape_type": "triangle",
      "class_true": "fragile",
      "radius": 0.1608,
      "center": [
        0.7784,
        3.0631
      ],
      "vertices": [
        [
          0.7816250224347693,
          2.8257131732164034
        ],
        [
          1.005686771254845,
          3.1319046010688614
        ],
        [
          0.5479155843285581,
          3.2318113294491453
        ]
      ]
    },
    {
      "id": 31,
      "shape_type": "diamond",
      "class_true": "movable",
      "radius": 0.1636,
      "center": [
        5.2849,
        4.6462
      ],
      "vertices": [
        [
          5.251936007544472,
          4.471260846238358
        ],
        [
          5.052787122436251,
          4.68996295803234
        ],
        [
          5.317921639212752,
          4.821091063931445
        ],
        [
          5.517070524320974,
          4.602388952137463
        ]
      ]
    },
    {
      "id": 32,
      "shape_type": "triangle",
      "class_true": "movable",
      "radius": 0.1645,
      "center": [
        1.3209,
        1.2552
      ],
      "vertices": [
        [
          1.2811553862250429,
          0.9910687403691689
        ],
        [
          1.5548399314932362,
          1.3841226064324832
        ],
        [
          1.1268157626270363,
          1.3903464710428377
        ]
      ]
    }
  ]
}